{
  "success": true,
  "message": "OK",
  "data": {
    "playerId": "439362",
    "history": {
      "terminated": [
        {
          "id": "6074406",
          "transferSource": {
            "competitionId": "CL2B",
            "countryId": 33,
            "clubId": "20694",
            "coachId": "21663"
          },
          "transferDestination": {
            "competitionId": "KAS1",
            "countryId": 81,
            "clubId": "19294",
            "coachId": "31549"
          },
          "details": {
            "playerId": "439362",
            "date": "2026-01-01T00:00:00+01:00",
            "contractUntilDate": "2026-12-31T00:00:00+01:00",
            "seasonId": 2025,
            "isPending": false,
            "marketValue": {
              "value": 450000,
              "currency": "EUR",
              "compact": {
                "prefix": "€",
                "content": "450.00",
                "suffix": "K"
              }
            },
            "age": 28,
            "fee": {
              "value": null,
              "currency": "",
              "compact": {
                "prefix": "",
                "content": "Free Transfer",
                "suffix": ""
              }
            },
            "season": {
              "id": 2025,
              "display": "25/26",
              "cyclicalName": "2026",
              "nonCyclicalName": "25/26"
            }
          },
          "typeDetails": {
            "type": "STANDARD",
            "name": "",
            "feeDescription": ""
          },
          "relativeUrl": "/thomas-jones/transfers/spieler/439362/transfer_id/6074406"
        },
        {
          "id": "5396466",
          "transferSource": {
            "competitionId": "CL2B",
            "countryId": 33,
            "clubId": "13394",
            "coachId": "115981"
          },
          "transferDestination": {
            "competitionId": "CL2B",
            "countryId": 33,
            "clubId": "20694",
            "coachId": "41404"
          },
          "details": {
            "playerId": "439362",
            "date": "2025-01-01T00:00:00+01:00",
            "contractUntilDate": "2025-12-31T00:00:00+01:00",
            "seasonId": 2024,
            "isPending": false,
            "marketValue": {
              "value": 275000,
              "currency": "EUR",
              "compact": {
                "prefix": "€",
                "content": "275.00",
                "suffix": "K"
              }
            },
            "age": 27,
            "fee": {
              "value": null,
              "currency": "",
              "compact": {
                "prefix": "",
                "content": "Free Transfer",
                "suffix": ""
              }
            },
            "season": {
              "id": 2024,
              "display": "24/25",
              "cyclicalName": "2025",
              "nonCyclicalName": "24/25"
            }
          },
          "typeDetails": {
            "type": "STANDARD",
            "name": "",
            "feeDescription": ""
          },
          "relativeUrl": "/thomas-jones/transfers/spieler/439362/transfer_id/5396466"
        },
        {
          "id": "2063379",
          "transferSource": {
            "competitionId": "",
            "countryId": 33,
            "clubId": "20683",
            "coachId": "17913"
          },
          "transferDestination": {
            "competitionId": "CL2B",
            "countryId": 33,
            "clubId": "13394",
            "coachId": "55669"
          },
          "details": {
            "playerId": "439362",
            "date": "2018-01-01T00:00:00+01:00",
            "contractUntilDate": null,
            "seasonId": 2017,
            "isPending": false,
            "marketValue": {
              "value": 0,
              "currency": "EUR",
              "compact": {
                "prefix": "€",
                "content": "0.00",
                "suffix": ""
              }
            },
            "age": 20,
            "fee": {
              "value": null,
              "currency": "",
              "compact": {
                "prefix": "",
                "content": "?",
                "suffix": ""
              }
            },
            "season": {
              "id": 2017,
              "display": "17/18",
              "cyclicalName": "2018",
              "nonCyclicalName": "17/18"
            }
          },
          "typeDetails": {
            "type": "STANDARD",
            "name": "",
            "feeDescription": ""
          },
          "relativeUrl": "/thomas-jones/transfers/spieler/439362/transfer_id/2063379"
        },
        {
          "id": "1494552",
          "transferSource": {
            "competitionId": "",
            "countryId": 33,
            "clubId": "45760",
            "coachId": "0"
          },
          "transferDestination": {
            "competitionId": "",
            "countryId": 33,
            "clubId": "20683",
            "coachId": "0"
          },
          "details": {
            "playerId": "439362",
            "date": "2015-09-01T00:00:00+02:00",
            "contractUntilDate": null,
            "seasonId": 2015,
            "isPending": false,
            "marketValue": {
              "value": 0,
              "currency": "EUR",
              "compact": {
                "prefix": "€",
                "content": "0.00",
                "suffix": ""
              }
            },
            "age": 17,
            "fee": {
              "value": null,
              "currency": "",
              "compact": {
                "prefix": "",
                "content": "Free Transfer",
                "suffix": ""
              }
            },
            "season": {
              "id": 2015,
              "display": "15/16",
              "cyclicalName": "2016",
              "nonCyclicalName": "15/16"
            }
          },
          "typeDetails": {
            "type": "STANDARD",
            "name": "",
            "feeDescription": ""
          },
          "relativeUrl": "/thomas-jones/transfers/spieler/439362/transfer_id/1494552"
        }
      ],
      "pending": [],
      "url": "",
      "feeSum": {
        "value": 0,
        "currency": "EUR",
        "compact": {
          "prefix": "€",
          "content": "0.00",
          "suffix": ""
        }
      },
      "averageAge": 28,
      "totalMarketValue": {
        "value": 350000,
        "currency": "EUR",
        "compact": {
          "prefix": "€",
          "content": "350.00",
          "suffix": "K"
        }
      }
    },
    "clubIds": [
      "20694",
      "19294",
      "13394",
      "20683",
      "45760"
    ],
    "coachIds": [
      "21663",
      "31549",
      "115981",
      "41404",
      "17913",
      "55669"
    ],
    "competitionIds": [
      "CL2B",
      "KAS1"
    ],
    "mostRecentTransfer": {
      "id": "6074406",
      "transferSource": {
        "competitionId": "CL2B",
        "countryId": 33,
        "clubId": "20694",
        "coachId": "21663"
      },
      "transferDestination": {
        "competitionId": "KAS1",
        "countryId": 81,
        "clubId": "19294",
        "coachId": "31549"
      },
      "details": {
        "playerId": "439362",
        "date": "2026-01-01T00:00:00+01:00",
        "contractUntilDate": "2026-12-31T00:00:00+01:00",
        "seasonId": 2025,
        "isPending": false,
        "marketValue": {
          "value": 450000,
          "currency": "EUR",
          "compact": {
            "prefix": "€",
            "content": "450.00",
            "suffix": "K"
          }
        },
        "age": 28,
        "fee": {
          "value": null,
          "currency": "",
          "compact": {
            "prefix": "",
            "content": "Free Transfer",
            "suffix": ""
          }
        },
        "season": {
          "id": 2025,
          "display": "25/26",
          "cyclicalName": "2026",
          "nonCyclicalName": "25/26"
        }
      },
      "typeDetails": {
        "type": "STANDARD",
        "name": "",
        "feeDescription": ""
      },
      "relativeUrl": "/thomas-jones/transfers/spieler/439362/transfer_id/6074406"
    }
  }
}