{
  "success": true,
  "message": "OK",
  "data": {
    "playerId": "639580",
    "history": {
      "terminated": [
        {
          "id": "5076979",
          "transferSource": {
            "competitionId": "RLB3",
            "countryId": 40,
            "clubId": "28",
            "coachId": "5716"
          },
          "transferDestination": {
            "competitionId": "L3",
            "countryId": 40,
            "clubId": "108",
            "coachId": "19998"
          },
          "details": {
            "playerId": "639580",
            "date": "2024-07-01T00:00:00+02:00",
            "contractUntilDate": "2027-06-30T00:00:00+02:00",
            "seasonId": 2024,
            "isPending": false,
            "marketValue": {
              "value": 200000,
              "currency": "EUR",
              "compact": {
                "prefix": "€",
                "content": "200.00",
                "suffix": "K"
              }
            },
            "age": 20,
            "fee": {
              "value": null,
              "currency": "",
              "compact": {
                "prefix": "",
                "content": "?",
                "suffix": ""
              }
            },
            "remainingContractPeriod": {
              "days": 364,
              "daysDisplay": "11 Months, 29 Days"
            },
            "season": {
              "id": 2024,
              "display": "24/25",
              "cyclicalName": "2025",
              "nonCyclicalName": "24/25"
            }
          },
          "typeDetails": {
            "type": "STANDARD",
            "name": "",
            "feeDescription": ""
          },
          "relativeUrl": "/justin-janitzek/transfers/spieler/639580/transfer_id/5076979"
        },
        {
          "id": "4444982",
          "transferSource": {
            "competitionId": "C1",
            "countryId": 148,
            "clubId": "257",
            "coachId": "472"
          },
          "transferDestination": {
            "competitionId": "RLB3",
            "countryId": 40,
            "clubId": "28",
            "coachId": "5716"
          },
          "details": {
            "playerId": "639580",
            "date": "2024-06-30T00:00:00+02:00",
            "contractUntilDate": "2025-06-30T00:00:00+02:00",
            "seasonId": 2023,
            "isPending": false,
            "marketValue": {
              "value": 200000,
              "currency": "EUR",
              "compact": {
                "prefix": "€",
                "content": "200.00",
                "suffix": "K"
              }
            },
            "age": 20,
            "remainingContractPeriod": {
              "days": 0,
              "daysDisplay": "Unknown"
            },
            "season": {
              "id": 2023,
              "display": "23/24",
              "cyclicalName": "2024",
              "nonCyclicalName": "23/24"
            }
          },
          "typeDetails": {
            "type": "RETURNED_FROM_PREVIOUS_LOAN",
            "name": "End of loan",
            "feeDescription": "End of loan"
          },
          "relativeUrl": "/justin-janitzek/transfers/spieler/639580/transfer_id/4444982"
        },
        {
          "id": "4444981",
          "transferSource": {
            "competitionId": "RLB3",
            "countryId": 40,
            "clubId": "28",
            "coachId": "5716"
          },
          "transferDestination": {
            "competitionId": "C1",
            "countryId": 148,
            "clubId": "257",
            "coachId": "472"
          },
          "details": {
            "playerId": "639580",
            "date": "2023-07-01T00:00:00+02:00",
            "contractUntilDate": "2024-06-30T00:00:00+02:00",
            "seasonId": 2023,
            "isPending": false,
            "marketValue": {
              "value": 500000,
              "currency": "EUR",
              "compact": {
                "prefix": "€",
                "content": "500.00",
                "suffix": "K"
              }
            },
            "age": 19,
            "remainingContractPeriod": {
              "days": 730,
              "daysDisplay": "1 Year, 11 Months, 29 Days"
            },
            "season": {
              "id": 2023,
              "display": "23/24",
              "cyclicalName": "2024",
              "nonCyclicalName": "23/24"
            }
          },
          "typeDetails": {
            "type": "ACTIVE_LOAN_TRANSFER",
            "name": "loan transfer",
            "feeDescription": "loan transfer"
          },
          "relativeUrl": "/justin-janitzek/transfers/spieler/639580/transfer_id/4444981"
        },
        {
          "id": "3807390",
          "transferSource": {
            "competitionId": "AJ3",
            "countryId": 40,
            "clubId": "1462",
            "coachId": "44682"
          },
          "transferDestination": {
            "competitionId": "RLB3",
            "countryId": 40,
            "clubId": "28",
            "coachId": "70585"
          },
          "details": {
            "playerId": "639580",
            "date": "2022-01-01T00:00:00+01:00",
            "contractUntilDate": "2025-06-30T00:00:00+02:00",
            "seasonId": 2021,
            "isPending": false,
            "marketValue": {
              "value": 300000,
              "currency": "EUR",
              "compact": {
                "prefix": "€",
                "content": "300.00",
                "suffix": "K"
              }
            },
            "age": 17,
            "fee": {
              "value": null,
              "currency": "",
              "compact": {
                "prefix": "",
                "content": "-",
                "suffix": ""
              }
            },
            "remainingContractPeriod": {
              "days": 911,
              "daysDisplay": "2 Years, 5 Months, 29 Days"
            },
            "season": {
              "id": 2021,
              "display": "21/22",
              "cyclicalName": "2022",
              "nonCyclicalName": "21/22"
            }
          },
          "typeDetails": {
            "type": "STANDARD",
            "name": "",
            "feeDescription": ""
          },
          "relativeUrl": "/justin-janitzek/transfers/spieler/639580/transfer_id/3807390"
        },
        {
          "id": "3419660",
          "transferSource": {
            "competitionId": "BJ3",
            "countryId": 40,
            "clubId": "21058",
            "coachId": "48142"
          },
          "transferDestination": {
            "competitionId": "AJ3",
            "countryId": 40,
            "clubId": "1462",
            "coachId": "44682"
          },
          "details": {
            "playerId": "639580",
            "date": "2021-07-01T00:00:00+02:00",
            "contractUntilDate": "2024-06-30T00:00:00+02:00",
            "seasonId": 2021,
            "isPending": false,
            "marketValue": {
              "value": null,
              "currency": "EUR",
              "compact": {
                "prefix": "€",
                "content": "",
                "suffix": ""
              }
            },
            "age": 17,
            "fee": {
              "value": null,
              "currency": "",
              "compact": {
                "prefix": "",
                "content": "-",
                "suffix": ""
              }
            },
            "remainingContractPeriod": {
              "days": 364,
              "daysDisplay": "11 Months, 29 Days"
            },
            "season": {
              "id": 2021,
              "display": "21/22",
              "cyclicalName": "2022",
              "nonCyclicalName": "21/22"
            }
          },
          "typeDetails": {
            "type": "STANDARD",
            "name": "",
            "feeDescription": ""
          },
          "relativeUrl": "/justin-janitzek/transfers/spieler/639580/transfer_id/3419660"
        },
        {
          "id": "2548863",
          "transferSource": {
            "competitionId": "",
            "countryId": 40,
            "clubId": "18936",
            "coachId": "48142"
          },
          "transferDestination": {
            "competitionId": "BJ3",
            "countryId": 40,
            "clubId": "21058",
            "coachId": "49850"
          },
          "details": {
            "playerId": "639580",
            "date": "2019-07-01T00:00:00+02:00",
            "contractUntilDate": "2022-06-30T00:00:00+02:00",
            "seasonId": 2019,
            "isPending": false,
            "marketValue": {
              "value": null,
              "currency": "EUR",
              "compact": {
                "prefix": "€",
                "content": "",
                "suffix": ""
              }
            },
            "age": 15,
            "fee": {
              "value": null,
              "currency": "",
              "compact": {
                "prefix": "",
                "content": "-",
                "suffix": ""
              }
            },
            "season": {
              "id": 2019,
              "display": "19/20",
              "cyclicalName": "2020",
              "nonCyclicalName": "19/20"
            }
          },
          "typeDetails": {
            "type": "STANDARD",
            "name": "",
            "feeDescription": ""
          },
          "relativeUrl": "/justin-janitzek/transfers/spieler/639580/transfer_id/2548863"
        },
        {
          "id": "2335374",
          "transferSource": {
            "competitionId": "",
            "countryId": 40,
            "clubId": "19210",
            "coachId": "15821"
          },
          "transferDestination": {
            "competitionId": "",
            "countryId": 40,
            "clubId": "18936",
            "coachId": "61269"
          },
          "details": {
            "playerId": "639580",
            "date": "2018-07-01T00:00:00+02:00",
            "contractUntilDate": null,
            "seasonId": 2018,
            "isPending": false,
            "marketValue": {
              "value": null,
              "currency": "EUR",
              "compact": {
                "prefix": "€",
                "content": "",
                "suffix": ""
              }
            },
            "age": 14,
            "fee": {
              "value": null,
              "currency": "",
              "compact": {
                "prefix": "",
                "content": "?",
                "suffix": ""
              }
            },
            "season": {
              "id": 2018,
              "display": "18/19",
              "cyclicalName": "2019",
              "nonCyclicalName": "18/19"
            }
          },
          "typeDetails": {
            "type": "STANDARD",
            "name": "",
            "feeDescription": ""
          },
          "relativeUrl": "/justin-janitzek/transfers/spieler/639580/transfer_id/2335374"
        }
      ],
      "pending": [],
      "url": "",
      "feeSum": {
        "value": 0,
        "currency": "EUR",
        "compact": {
          "prefix": "€",
          "content": "0.00",
          "suffix": ""
        }
      },
      "averageAge": 22,
      "totalMarketValue": {
        "value": 500000,
        "currency": "EUR",
        "compact": {
          "prefix": "€",
          "content": "500.00",
          "suffix": "K"
        }
      }
    },
    "clubIds": [
      "28",
      "108",
      "257",
      "1462",
      "21058",
      "18936",
      "19210"
    ],
    "coachIds": [
      "5716",
      "19998",
      "472",
      "44682",
      "70585",
      "48142",
      "49850",
      "15821",
      "61269"
    ],
    "competitionIds": [
      "RLB3",
      "L3",
      "C1",
      "AJ3",
      "BJ3"
    ],
    "mostRecentTransfer": {
      "id": "5076979",
      "transferSource": {
        "competitionId": "RLB3",
        "countryId": 40,
        "clubId": "28",
        "coachId": "5716"
      },
      "transferDestination": {
        "competitionId": "L3",
        "countryId": 40,
        "clubId": "108",
        "coachId": "19998"
      },
      "details": {
        "playerId": "639580",
        "date": "2024-07-01T00:00:00+02:00",
        "contractUntilDate": "2027-06-30T00:00:00+02:00",
        "seasonId": 2024,
        "isPending": false,
        "marketValue": {
          "value": 200000,
          "currency": "EUR",
          "compact": {
            "prefix": "€",
            "content": "200.00",
            "suffix": "K"
          }
        },
        "age": 20,
        "fee": {
          "value": null,
          "currency": "",
          "compact": {
            "prefix": "",
            "content": "?",
            "suffix": ""
          }
        },
        "remainingContractPeriod": {
          "days": 364,
          "daysDisplay": "11 Months, 29 Days"
        },
        "season": {
          "id": 2024,
          "display": "24/25",
          "cyclicalName": "2025",
          "nonCyclicalName": "24/25"
        }
      },
      "typeDetails": {
        "type": "STANDARD",
        "name": "",
        "feeDescription": ""
      },
      "relativeUrl": "/justin-janitzek/transfers/spieler/639580/transfer_id/5076979"
    }
  }
}